{
  "questGivers": [
    {
      "id": "acorninnkeeper",
      "name": "Acorn Inn Keeper",
      "shape": "trader"
    }
  ],
  "questGiverShapes": [
    {
      "displayName": "Trader",
      "mod": "game",
      "name": "trader",
      "type": "humanoid",
      "textureAlternatives": [
        {
          "type": "traderclothes",
          "subTypes": [
            "set1", 
            "set2", 
            "set3",
            "set4",
            "set5"
          ]
        }
      ]
    }
  ]
}
